{
  "airTemperature": [
    {
      "x": "2025-08-09T02:41:34.684569",
      "y": 16.417128
    },
    {
      "x": "2025-08-09T03:41:33.437634",
      "y": 16.062807
    },
    {
      "x": "2025-08-09T04:41:39.120114",
      "y": 16.075552
    },
    {
      "x": "2025-08-09T07:41:33.691858",
      "y": 23.289522
    },
    {
      "x": "2025-08-09T08:41:37.527833",
      "y": 26.052021
    },
    {
      "x": "2025-08-09T09:41:40.138363",
      "y": 28.722458
    },
    {
      "x": "2025-08-09T10:11:43.122329",
      "y": 29.92039
    },
    {
      "x": "2025-08-09T17:41:42.508501",
      "y": 34.627914
    },
    {
      "x": "2025-08-09T19:11:42.146814",
      "y": 24.93928
    },
    {
      "x": "2025-08-09T19:41:43.659113",
      "y": 23.63067
    },
    {
      "x": "2025-08-09T20:41:42.383513",
      "y": 22.191431
    },
    {
      "x": "2025-08-09T21:11:41.784562",
      "y": 21.706669
    },
    {
      "x": "2025-08-10T00:11:45.222960",
      "y": 18.853355
    }
  ],
  "airHumidity": [
    {
      "x": "2025-08-09T02:41:34.684569",
      "y": 62.204613
    },
    {
      "x": "2025-08-09T03:41:33.437634",
      "y": 62.08904
    },
    {
      "x": "2025-08-09T04:41:39.120114",
      "y": 61.750996
    },
    {
      "x": "2025-08-09T07:41:33.691858",
      "y": 61.64007
    },
    {
      "x": "2025-08-09T08:41:37.527833",
      "y": 62.02259
    },
    {
      "x": "2025-08-09T09:41:40.138363",
      "y": 62.29247
    },
    {
      "x": "2025-08-09T10:11:43.122329",
      "y": 62.31333
    },
    {
      "x": "2025-08-09T17:41:42.508501",
      "y": 59.55697
    },
    {
      "x": "2025-08-09T19:11:42.146814",
      "y": 60.975502
    },
    {
      "x": "2025-08-09T19:41:43.659113",
      "y": 60.493744
    },
    {
      "x": "2025-08-09T20:41:42.383513",
      "y": 59.779625
    },
    {
      "x": "2025-08-09T21:11:41.784562",
      "y": 59.576572
    },
    {
      "x": "2025-08-10T00:11:45.222960",
      "y": 60.141354
    }
  ],
  "!04c5ad60-0-temperature": [
    {
      "x": "2025-08-09T03:18:27.438436",
      "y": 18.4
    },
    {
      "x": "2025-08-09T04:48:09.021308",
      "y": 18.4
    },
    {
      "x": "2025-08-09T05:18:09.341308",
      "y": 18.9
    },
    {
      "x": "2025-08-09T16:04:06.583484",
      "y": 27.3
    },
    {
      "x": "2025-08-09T18:06:16.541539",
      "y": 24.5
    }
  ],
  "!04c5ad60-0-moisture": [
    {
      "x": "2025-08-09T03:18:27.438436",
      "y": 67.0
    },
    {
      "x": "2025-08-09T04:48:09.021308",
      "y": 68.0
    },
    {
      "x": "2025-08-09T05:18:09.341308",
      "y": 66.0
    },
    {
      "x": "2025-08-09T16:04:06.583484",
      "y": 57.0
    },
    {
      "x": "2025-08-09T18:06:16.541539",
      "y": 60.0
    }
  ],
  "!04c5ad60-1-temperature": [
    {
      "x": "2025-08-09T03:18:27.438436",
      "y": 20.9
    },
    {
      "x": "2025-08-09T04:48:09.021308",
      "y": 20.5
    },
    {
      "x": "2025-08-09T05:18:09.341308",
      "y": 20.4
    },
    {
      "x": "2025-08-09T16:04:06.583484",
      "y": 27.0
    },
    {
      "x": "2025-08-09T18:06:16.541539",
      "y": 26.1
    }
  ],
  "!04c5ad60-1-moisture": [
    {
      "x": "2025-08-09T03:18:27.438436",
      "y": 72.0
    },
    {
      "x": "2025-08-09T04:48:09.021308",
      "y": 72.0
    },
    {
      "x": "2025-08-09T05:18:09.341308",
      "y": 73.0
    },
    {
      "x": "2025-08-09T16:04:06.583484",
      "y": 65.0
    },
    {
      "x": "2025-08-09T18:06:16.541539",
      "y": 67.0
    }
  ],
  "!76208ba5-0-temperature": [
    {
      "x": "2025-08-09T03:25:48.434178",
      "y": 21.8
    },
    {
      "x": "2025-08-09T10:02:29.311141",
      "y": 23.3
    },
    {
      "x": "2025-08-09T19:59:26.878027",
      "y": 24.4
    },
    {
      "x": "2025-08-09T20:35:28.627382",
      "y": 24.2
    },
    {
      "x": "2025-08-10T01:05:58.110281",
      "y": 22.9
    }
  ],
  "!76208ba5-0-moisture": [
    {
      "x": "2025-08-09T03:25:48.434178",
      "y": 14.0
    },
    {
      "x": "2025-08-09T10:02:29.311141",
      "y": 13.0
    },
    {
      "x": "2025-08-09T19:59:26.878027",
      "y": 10.0
    },
    {
      "x": "2025-08-09T20:35:28.627382",
      "y": 10.0
    },
    {
      "x": "2025-08-10T01:05:58.110281",
      "y": 12.0
    }
  ],
  "!76208ba5-1-temperature": [
    {
      "x": "2025-08-09T03:25:48.434178",
      "y": 20.7
    },
    {
      "x": "2025-08-09T10:02:29.311141",
      "y": 23.4
    },
    {
      "x": "2025-08-09T19:59:26.878027",
      "y": 23.5
    },
    {
      "x": "2025-08-09T20:35:28.627382",
      "y": 23.3
    },
    {
      "x": "2025-08-10T01:05:58.110281",
      "y": 21.8
    }
  ],
  "!76208ba5-1-moisture": [
    {
      "x": "2025-08-09T03:25:48.434178",
      "y": 13.0
    },
    {
      "x": "2025-08-09T10:02:29.311141",
      "y": 10.0
    },
    {
      "x": "2025-08-09T19:59:26.878027",
      "y": 8.0
    },
    {
      "x": "2025-08-09T20:35:28.627382",
      "y": 9.0
    },
    {
      "x": "2025-08-10T01:05:58.110281",
      "y": 11.0
    }
  ],
  "!35c2d45c-0-temperature": [
    {
      "x": "2025-08-09T17:44:01.824795",
      "y": 26.7
    },
    {
      "x": "2025-08-09T21:20:21.506783",
      "y": 22.5
    },
    {
      "x": "2025-08-09T21:38:26.025953",
      "y": 22.4
    },
    {
      "x": "2025-08-10T00:38:43.598018",
      "y": 20.8
    }
  ],
  "!35c2d45c-0-moisture": [
    {
      "x": "2025-08-09T17:44:01.824795",
      "y": 64.0
    },
    {
      "x": "2025-08-09T21:20:21.506783",
      "y": 45.0
    },
    {
      "x": "2025-08-09T21:38:26.025953",
      "y": 45.0
    },
    {
      "x": "2025-08-10T00:38:43.598018",
      "y": 47.0
    }
  ],
  "!35c2d45c-1-temperature": [
    {
      "x": "2025-08-09T17:44:01.824795",
      "y": 25.4
    },
    {
      "x": "2025-08-09T21:20:21.506783",
      "y": 22.7
    },
    {
      "x": "2025-08-09T21:38:26.025953",
      "y": 22.6
    },
    {
      "x": "2025-08-10T00:38:43.598018",
      "y": 21.2
    }
  ],
  "!35c2d45c-1-moisture": [
    {
      "x": "2025-08-09T17:44:01.824795",
      "y": 59.0
    },
    {
      "x": "2025-08-09T21:20:21.506783",
      "y": 64.0
    },
    {
      "x": "2025-08-09T21:38:26.025953",
      "y": 64.0
    },
    {
      "x": "2025-08-10T00:38:43.598018",
      "y": 65.0
    }
  ]
}